coolstar4/__init__.py
coolstar4/galaxy.py
coolstar4-0.0.3.dist-info/METADATA
coolstar4-0.0.3.dist-info/WHEEL
coolstar4-0.0.3.dist-info/top_level.txt
coolstar4-0.0.3.dist-info/RECORD
