Metadata-Version: 2.1
Name: coolstar4
Version: 0.0.3
Summary: This is a kid's python library.
Home-page: UNKNOWN
Author: seale
Author-email: seale@outlook.com
License: GPL2
Platform: UNKNOWN
Requires-Dist: argon2-cffi (==19.2.0)
Requires-Dist: vpython (==7.6.1)
Requires-Dist: numpy (==1.19.3)
